grimoiressg/__main__.py
grimoiressg/arguments.py
grimoiressg/config.py
grimoiressg/content_files.py
grimoiressg/modules/__init__.py
grimoiressg/modules/markdown.py
grimoiressg/modules/sitemaps.py
grimoiressg/modules/tags.py
grimoiressg/modules/templating.py
grimoiressg/scripts.py
grimoiressg/utils/__init__.py
grimoiressg/utils/files.py
grimoiressg/utils/logger.py
grimoire_ssg-1.1.2.dist-info/LICENSE
grimoire_ssg-1.1.2.dist-info/METADATA
grimoire_ssg-1.1.2.dist-info/WHEEL
grimoire_ssg-1.1.2.dist-info/entry_points.txt
grimoire_ssg-1.1.2.dist-info/RECORD
