Metadata-Version: 2.3
Name: grimoire-ssg
Version: 1.1.2
Summary: A minimalistic Static Site Generator
License: BSD-2-Clause
Author: Sigma
Author-email: git@sigma-star.io
Requires-Python: >=3.10,<4.0
Classifier: License :: OSI Approved :: BSD License
Classifier: Programming Language :: Python :: 3
Classifier: Programming Language :: Python :: 3.10
Classifier: Programming Language :: Python :: 3.11
Classifier: Programming Language :: Python :: 3.12
Classifier: Programming Language :: Python :: 3.13
Requires-Dist: jinja2 (>=3.1.5,<4.0.0)
Requires-Dist: markdown (>=3.7,<4.0)
Requires-Dist: pyyaml (>=6.0.2,<7.0.0)
